[
  {
    "id": "1773126402815",
    "address": "ngõ 423 An Dương Vương - Tây Hồ",
    "price": "10tr5-11tr5",
    "price1": "10.500.000",
    "price2": "11.500.000",
    "type": "2n1k"
  },
  {
    "id": "1773126444381",
    "address": "5/54/218 Lạc Long Quân - Tây Hồ",
    "price": "9tr5-studio, 10tr-gác xép",
    "price1": "9.500.000",
    "price2": "10.000.000",
    "type": "studio"
  },
  {
    "id": "1773126501565",
    "address": "Số 12B ngõ 603 Lạc Long Quân - Tây Hồ",
    "price": "4tr5",
    "price1": "4.500.000",
    "price2": "4.500.000",
    "type": "studio"
  },
  {
    "id": "1773126792089",
    "address": "Số 44a Ngách 12a Ngõ 23 Xuân La - Tây Hồ",
    "price": "5tr8",
    "price1": "5.800.000",
    "price2": "5.800.000",
    "type": "1n1k"
  },
  {
    "id": "1773130141137",
    "address": "ngách 50/18 ngõ 445 Lạc Long Quân",
    "price": "3tr6",
    "price1": "3.600.000",
    "price2": "3.600.000",
    "type": null
  },
  {
    "id": "1773130204496",
    "address": "Số 499A Lạc Long Quân - Tây Hồ",
    "price": "4tr250k",
    "price1": "4.250.000",
    "price2": "4.250.000",
    "type": null
  },
  {
    "id": "1773131565003",
    "address": "Số 19 Ngách 46 ngõ 445 Lạc Long Quân - Tây Hồ",
    "price": "4tr8",
    "price1": "4.800.000",
    "price2": "4.800.000",
    "type": "studio"
  },
  {
    "id": "1773131584505",
    "address": "Số 12 Ngõ 569/12 Lạc Long Quân - Tây Hồ",
    "price": "3tr8",
    "price1": "3.800.000",
    "price2": "3.800.000",
    "type": "studio"
  },
  {
    "id": "1773137620485",
    "address": "Nhà ngõ 38 Xuân La, - Quận: Tây Hồ",
    "price": "4tr2",
    "price1": "4.200.000",
    "price2": "4.200.000",
    "type": "gác xép"
  },
  {
    "id": "1773142059559",
    "address": "43c ngõ 472 Lạc Long Quân, Tây Hồ",
    "price": "5tr-5tr5",
    "price1": "5.000.000",
    "price2": "5.500.000",
    "type": null
  },
  {
    "id": "1773142631784",
    "address": "269 Lạc Long Quân - Tây Hồ",
    "price": "4tr3",
    "price1": "4.300.000",
    "price2": "4.300.000",
    "type": null
  },
  {
    "id": "1773145651427",
    "address": "số 63 Võng Thị - Tây Hồ",
    "price": "6tr5",
    "price1": "6.500.000",
    "price2": "6.500.000",
    "type": "studio"
  },
  {
    "id": "1773145848455",
    "address": "25 ngõ 89 Tứ Liên - Tây Hồ",
    "price": "10tr-p301",
    "price1": "10.000.000",
    "price2": "10.000.000",
    "type": "2n1k"
  },
  {
    "id": "1773146362025",
    "address": "số 37 ngõ 50 Võng Thị - Tây Hồ",
    "price": "6tr",
    "price1": "6.000.000",
    "price2": "6.000.000",
    "type": "studio"
  },
  {
    "id": "1773146688660",
    "address": "535 Xuân Đỉnh - Tây Hồ",
    "price": "4tr6 - 4tr8 - 5tr5",
    "price1": "4.600.000",
    "price2": "5.500.000",
    "type": "studio"
  },
  {
    "id": "1773150222315",
    "address": "Ngõ 245 Lạc Long Quân - Tây Hồ",
    "price": "4tr3",
    "price1": "4.300.000",
    "price2": "4.300.000",
    "type": "studio"
  },
  {
    "id": "1773152818476",
    "address": "149 Vệ Hồ, Xuân La - Tây Hồ",
    "price": "4tr5",
    "price1": "4.500.000",
    "price2": "4.500.000",
    "type": "studio"
  },
  {
    "id": "1773155673343",
    "address": "ngách 46 Ngõ 445 Lạc Long Quân - Phường Xuân La - Tây Hồ",
    "price": "6tr2 - 6tr8",
    "price1": "6.200.000",
    "price2": "6.800.000",
    "type": null
  },
  {
    "id": "1773155737455",
    "address": "Số 48 Ngõ 445 Lạc Long Quân, Phường Xuân La, Q. Tây Hồ, Tp. Hà Nội",
    "price": "8tr5",
    "price1": "8.500.000",
    "price2": "8.500.000",
    "type": "2n1k"
  },
  {
    "id": "1773165659130",
    "address": "50 Võng Thị - Tây Hồ",
    "price": "6tr",
    "price1": "6.000.000",
    "price2": "6.000.000",
    "type": "studio"
  },
  {
    "id": "1773174444118",
    "address": "Ngõ 373 An Dương Vương - Tây Hồ",
    "price": "4tr6",
    "price1": "4.600.000",
    "price2": "4.600.000",
    "type": "studio"
  },
  {
    "id": "1773241854670",
    "address": "444 Thụy Khuê – Tây Hồ",
    "price": "5tr8",
    "price1": "5.800.000",
    "price2": "5.800.000",
    "type": null
  },
  {
    "id": "1773247060787",
    "address": "16 THƯỢNG THỤY- CIPUTRA- TÂY HỒ",
    "price": "3tr7 - 4tr6",
    "price1": "3.700.000",
    "price2": "4.600.000",
    "type": "studio"
  },
  {
    "id": "1773250506402",
    "address": "Ngõ 61 Lạc Long Quân - Tây Hồ",
    "price": "5tr5 - 5tr8 - 6tr( sofa)",
    "price1": "5.500.000",
    "price2": "6.000.000",
    "type": "studio"
  },
  {
    "id": "1773252486444",
    "address": "số nhà 14 ngách 42/30 ngõ 175 LẠC LONG QUÂN - TÂY HỒ",
    "price": "4tr3",
    "price1": "4.300.000",
    "price2": "4.300.000",
    "type": "studio"
  },
  {
    "id": "1773254057395",
    "address": "Số 25b ngõ 210a Võ Chí Công, Tây Hồ",
    "price": "6tr5 - P203\n5tr2 - 5tr5 - P303-703-604",
    "price1": "5.200.000",
    "price2": "6.500.000",
    "type": "studio"
  },
  {
    "id": "1773261909272",
    "address": "179 Phố Nguyễn Đình Thi- Quận: Tây Hồ",
    "price": "4tr5 - p603,503",
    "price1": "4.500.000",
    "price2": "4.500.000",
    "type": "studio"
  },
  {
    "id": "1773262151408",
    "address": "127 ngõ 56 Tứ Liên – Tây Hồ",
    "price": "5tr8/tháng",
    "price1": "5.800.000",
    "price2": "5.800.000",
    "type": null
  },
  {
    "id": "1773264278337",
    "address": "Ngõ 521 An Dương Vương Tây Hồ",
    "price": "3tr8-3tr9 , p601-602",
    "price1": "3.800.000",
    "price2": "3.900.000",
    "type": null
  },
  {
    "id": "1773267853868",
    "address": "ngõ 423 An Dương Vương - Tây Hồ",
    "price": "10tr5 tầng 2",
    "price1": "10.500.000",
    "price2": "10.500.000",
    "type": "2n1k"
  },
  {
    "id": "1773269674109",
    "address": "mặt đường Yên Phụ- P.Tây Hồ",
    "price": "11tr-",
    "price1": "11.000.000",
    "price2": "11.000.000",
    "type": "2n1k"
  },
  {
    "id": "1773269691245",
    "address": "mặt đường Yên Phụ- P.Tây Hồ",
    "price": "9tr5-",
    "price1": "9.500.000",
    "price2": "9.500.000",
    "type": "1n1k"
  },
  {
    "id": "1773269697859",
    "address": "mặt đường Yên Phụ- P.Tây Hồ",
    "price": "11tr5",
    "price1": "11.500.000",
    "price2": "11.500.000",
    "type": "2n1k"
  },
  {
    "id": "1773272951902",
    "address": "Số 9 ngách 38 ngõ 445 Lạc Long Quân, Tây Hồ",
    "price": "4tr5",
    "price1": "4.500.000",
    "price2": "4.500.000",
    "type": "studio"
  },
  {
    "id": "1773273377617",
    "address": "179 Nguyễn Đình Thi - Tây Hồ",
    "price": "4tr5",
    "price1": "4.500.000",
    "price2": "4.500.000",
    "type": "studio"
  },
  {
    "id": "1773271619274",
    "address": "d ngõ 125 Trịnh Công Sơn - Tây Hồ",
    "price": "2tr9",
    "price1": "2.900.000",
    "price2": "2.900.000",
    "type": null
  },
  {
    "id": "1773275666274",
    "address": "Ngõ 4 An Dương Vương - Tây Hồ",
    "price": "5tr5",
    "price1": "5.500.000",
    "price2": "5.500.000",
    "type": "2N1B"
  },
  {
    "id": "1773275723238",
    "address": "Ngõ 4 An Dương Vương - Tây Hồ",
    "price": "4tr",
    "price1": "4.000.000",
    "price2": "4.000.000",
    "type": "1N1B"
  },
  {
    "id": "1773279506917",
    "address": "Tòa nhà số 11A Ngõ 376/12 Thụy Khuê – Tây Hồ – Hà Nội",
    "price": "5tr5",
    "price1": "5.500.000",
    "price2": "5.500.000",
    "type": "studio"
  },
  {
    "id": "1773282188558",
    "address": "Số 25b ngõ 210a Võ Chí Công - Tây Hồ",
    "price": "5tr5",
    "price1": "5.500.000",
    "price2": "5.500.000",
    "type": "studio"
  },
  {
    "id": "1773282207473",
    "address": "225 Âu Cơ - Tây Hồ",
    "price": "8tr5",
    "price1": "8.500.000",
    "price2": "8.500.000",
    "type": "1n1k"
  },
  {
    "id": "1773286006939",
    "address": "228 Âu Cơ - Tây Hồ ( Ngay chợ Hoa Quảng An)",
    "price": "7tr",
    "price1": "7.000.000",
    "price2": "7.000.000",
    "type": "1n1k"
  },
  {
    "id": "1773286190413",
    "address": "26 Ngõ 35A Tứ Liên - Tây Hồ",
    "price": "4tr",
    "price1": "4.000.000",
    "price2": "4.000.000",
    "type": null
  },
  {
    "id": "1773286197672",
    "address": "Số 19 Ngách 46 ngõ 445 Lạc Long Quân",
    "price": "4tr8",
    "price1": "4.800.000",
    "price2": "4.800.000",
    "type": "studio"
  },
  {
    "id": "1773286678319",
    "address": "32/18 Tô Ngọc Vân - Tây Hồ",
    "price": "8tr",
    "price1": "8.000.000",
    "price2": "8.000.000",
    "type": "1n1k"
  },
  {
    "id": "1773287733706",
    "address": "Ngõ 61 Lạc Long Quân - Tây Hồ",
    "price": "5tr5 - 5tr8 - 6tr( sofa)",
    "price1": "5.500.000",
    "price2": "6.000.000",
    "type": "studio"
  },
  {
    "id": "1773296019997",
    "address": "444 Thụy Khuê – Tây Hồ – Hà Nội",
    "price": "5tr8 (có thể thương lượng)",
    "price1": "5.800.000",
    "price2": "5.800.000",
    "type": null
  },
  {
    "id": "1773300023169",
    "address": "Ngõ 61 Lạc Long Quân - Tây Hồ",
    "price": "5tr5",
    "price1": "5.500.000",
    "price2": "5.500.000",
    "type": "studio"
  },
  {
    "id": "1773300101807",
    "address": "Ngõ 61 Lạc Long Quân - Tây Hồ",
    "price": "5tr8",
    "price1": "5.800.000",
    "price2": "5.800.000",
    "type": "studio"
  },
  {
    "id": "1773301179073",
    "address": "Nhà A1 – Số 32 ngõ 61 Lạc Long Quân",
    "price": "5tr8",
    "price1": "5.800.000",
    "price2": "5.800.000",
    "type": "studio"
  },
  {
    "id": "1773310097286",
    "address": "104 Nghi Tàm - Tây Hồ",
    "price": "6tr9",
    "price1": "6.900.000",
    "price2": "6.900.000",
    "type": "1n1k"
  },
  {
    "id": "1773321842778",
    "address": "Ngõ 123A Thụy khuê - Tây Hồ",
    "price": "7tr",
    "price1": "7.000.000",
    "price2": "7.000.000",
    "type": "1n1k"
  },
  {
    "id": "1773321871448",
    "address": "Ngõ 565 Lạc Long Quân - Tây Hồ",
    "price": "5tr ( có fixx )",
    "price1": "5.000.000",
    "price2": "5.000.000",
    "type": null
  },
  {
    "id": "1773376502199",
    "address": "Nhà số 11 ngõ 89 Tứ Liên",
    "price": "6tr - 6tr3",
    "price1": "6.000.000",
    "price2": "6.300.000",
    "type": "2n1k"
  },
  {
    "id": "1773376849355",
    "address": "179 Nhật Chiêu - 472 Lạc Long quân",
    "price": "7tr5",
    "price1": "7.500.000",
    "price2": "7.500.000",
    "type": "1n1k"
  },
  {
    "id": "1773377601095",
    "address": "Ngõ 217 Trích Sài",
    "price": "10tr",
    "price1": "10.000.000",
    "price2": "10.000.000",
    "type": "1n1k"
  },
  {
    "id": "1773384179235",
    "address": "46 Lạc Long Quân",
    "price": "6tr3",
    "price1": "6.300.000",
    "price2": "6.300.000",
    "type": "studio"
  },
  {
    "id": "1773387134569",
    "address": "Số 127 ngõ 56 Tứ Liên",
    "price": "3tr",
    "price1": "3.000.000",
    "price2": "3.000.000",
    "type": null
  },
  {
    "id": "1773387236739",
    "address": "127 Ngõ 56 Tứ Liên",
    "price": "5tr5",
    "price1": "5.500.000",
    "price2": "5.500.000",
    "type": null
  },
  {
    "id": "1773387387788",
    "address": "Số 127 ngõ 56 Tứ Liên",
    "price": "4tr5",
    "price1": "4.500.000",
    "price2": "4.500.000",
    "type": null
  },
  {
    "id": "1773402394731",
    "address": "Ngõ 12 Xuân La",
    "price": "4tr5 - 5tr",
    "price1": "4.500.000",
    "price2": "5.000.000",
    "type": "studio"
  },
  {
    "id": "1773404883517",
    "address": "Ngõ 167 Thuỵ Khuê",
    "price": "5tr5 triệu/tháng",
    "price1": "5.500.000",
    "price2": "5.500.000",
    "type": "studio"
  },
  {
    "id": "1773406222844",
    "address": "SỐ 4 NGÁCH 1 NGÕ 34 ÂU CƠ",
    "price": "4tr8 - 6tr",
    "price1": "4.800.000",
    "price2": "6.000.000",
    "type": "studio"
  },
  {
    "id": "1773409152294",
    "address": "Ngõ 217 Trích Sài",
    "price": "10tr",
    "price1": "10.000.000",
    "price2": "10.000.000",
    "type": "1n1k"
  },
  {
    "id": "1773412527531",
    "address": "11/89 Tứ Liên",
    "price": "6tr - 6tr3",
    "price1": "6.000.000",
    "price2": "6.300.000",
    "type": "2n1k"
  },
  {
    "id": "1773416270486",
    "address": "Ngõ 189 An Dương",
    "price": "8tr5",
    "price1": "8.500.000",
    "price2": "8.500.000",
    "type": "2N1K"
  },
  {
    "id": "1773417237558",
    "address": "Số 5, ngõ 54/9 Âu Cơ, Tây Hồ",
    "price": "4tr5",
    "price1": "4.500.000",
    "price2": "4.500.000",
    "type": "null"
  },
  {
    "id": "1773417580666",
    "address": "Số 5, ngõ 54/9 Âu Cơ, Tây Hồ",
    "price": "5tr",
    "price1": "5.000.000",
    "price2": "5.000.000",
    "type": "null"
  },
  {
    "id": "1773417752511",
    "address": "ngõ 89 Tứ Liên,Hồng Hà,HN",
    "price": "4tr/tháng",
    "price1": "4.000.000",
    "price2": "4.000.000",
    "type": "null"
  },
  {
    "id": "1773417837011",
    "address": "ngách 69 ngõ 28 Tứ Liên Tây Hồ,HN",
    "price": "5tr",
    "price1": "5.000.000",
    "price2": "5.000.000",
    "type": "1n1k"
  },
  {
    "id": "1773421147523",
    "address": "189 Đường An Dương Vương - Tây Hồ",
    "price": "7tr",
    "price1": "7.000.000",
    "price2": "7.000.000",
    "type": "studio"
  },
  {
    "id": "1773421797869",
    "address": "số 2B ngách 46 Ngõ 445 Lạc Long Quân - Tây Hồ",
    "price": "6tr2,6tr5",
    "price1": "6.200.000",
    "price2": "6.500.000",
    "type": "studio"
  },
  {
    "id": "1773421806366",
    "address": "số 2B ngách 46 Ngõ 445 Lạc Long Quân - Tây Hồ",
    "price": "6tr8",
    "price1": "6.800.000",
    "price2": "6.800.000",
    "type": "1n1k"
  },
  {
    "id": "1773421843910",
    "address": "Số 48 Ngõ 445 Lạc Long Quân - Tây Hồ",
    "price": "8tr5",
    "price1": "8.500.000",
    "price2": "8.500.000",
    "type": "2n1k"
  },
  {
    "id": "1773422058859",
    "address": "Số 17 ngõ 105 Phú Xá - Tây Hồ",
    "price": "4tr5",
    "price1": "4.500.000",
    "price2": "4.500.000",
    "type": "gác xép"
  },
  {
    "id": "1773422065453",
    "address": "Số 17 ngõ 105 Phú Xá - Tây Hồ",
    "price": "5tr",
    "price1": "5.000.000",
    "price2": "5.000.000",
    "type": "studio"
  },
  {
    "id": "1773427561440",
    "address": "Ngõ 373 An Dương Vương - Tây Hồ",
    "price": "4tr6",
    "price1": "4.600.000",
    "price2": "4.600.000",
    "type": "studio"
  },
  {
    "id": "1773483429200",
    "address": "Số 2B, ngách 46, Ngõ 445 Lạc Long Quân, Phường Xuân La, Q. Tây Hồ, Tp. Hà Nội",
    "price": "6tr2,6tr8",
    "price1": "6.200.000",
    "price2": "6.800.000",
    "type": "studio"
  },
  {
    "id": "1773484591476",
    "address": "ngõ 603 ngách 569/12 Lạc Long Quân - Tây Hồ",
    "price": "5tr3",
    "price1": "5.300.000",
    "price2": "5.300.000",
    "type": "null"
  },
  {
    "id": "1773485685199",
    "address": "số 16, ngõ 603, ngách 569/12 Lạc Long Quân - TÂY HỒ",
    "price": "5tr3",
    "price1": "5.300.000",
    "price2": "5.300.000",
    "type": "studio"
  },
  {
    "id": "1773488978098",
    "address": "353 Thụy Khuê",
    "price": "5tr2",
    "price1": "5.200.000",
    "price2": "5.200.000",
    "type": "studio"
  },
  {
    "id": "1773490615343",
    "address": "5/497 Âu Cơ, Tây Hồ, Hà Nội",
    "price": "1tr9",
    "price1": "1.900.000",
    "price2": "1.900.000",
    "type": "null"
  },
  {
    "id": "1773496870164",
    "address": "ngõ 603, ngách 569/12 Lạc Long Quân - Hồ Tây",
    "price": "4tr7",
    "price1": "4.700.000",
    "price2": "4.700.000",
    "type": "studio"
  },
  {
    "id": "1773499398591",
    "address": "Số 6 ngõ 141 đường An Dương Vương - Tây Hồ",
    "price": "4tr",
    "price1": "4.000.000",
    "price2": "4.000.000",
    "type": "studio"
  },
  {
    "id": "1773499418990",
    "address": "Số 6 ngõ 141 đường An Dương Vương - Tây Hồ",
    "price": "4tr5",
    "price1": "4.500.000",
    "price2": "4.500.000",
    "type": "1n1k"
  },
  {
    "id": "1773499463328",
    "address": "Số 6 ngõ 141 đường An Dương Vương - Tây Hồ",
    "price": "4tr2",
    "price1": "4.200.000",
    "price2": "4.200.000",
    "type": "gác xép"
  },
  {
    "id": "1773500285403",
    "address": "Ngõ 46 Lạc Long quân - Tây Hồ",
    "price": "7tr5",
    "price1": "7.500.000",
    "price2": "7.500.000",
    "type": "1n1k"
  },
  {
    "id": "1773501404893",
    "address": "Số 6 Ngõ 245 Đường Lạc Long Quân",
    "price": "3tr7",
    "price1": "3.700.000",
    "price2": "3.700.000",
    "type": null
  },
  {
    "id": "1773506092405",
    "address": "Số 91C ngõ 91 Đồng Cổ, 353 Thuỵ Khuê, Tây Hồ",
    "price": "5tr2",
    "price1": "5.200.000",
    "price2": "5.200.000",
    "type": null
  },
  {
    "id": "1773506175768",
    "address": "Số 91C ngõ 91 Đồng Cổ, 353 Thuỵ Khuê, Tây Hồ",
    "price": "6tr",
    "price1": "6.000.000",
    "price2": "6.000.000",
    "type": null
  },
  {
    "id": "1773506184335",
    "address": "số 16, ngõ 603, ngách 569/12 Lạc Long Quân, Tây Hồ",
    "price": "5tr3",
    "price1": "5.300.000",
    "price2": "5.300.000",
    "type": null
  },
  {
    "id": "1773511471559",
    "address": "ngõ 224 Đường Bưởi, quận Ba Đình",
    "price": "11tr",
    "price1": "11.000.000",
    "price2": "11.000.000",
    "type": "1n1k"
  },
  {
    "id": "1773513240359",
    "address": "số 16, ngõ 603, ngách 569/12 Lạc Long Quân",
    "price": "5tr3",
    "price1": "5.300.000",
    "price2": "5.300.000",
    "type": null
  },
  {
    "id": "1773513242766",
    "address": "số 16, ngõ 603, ngách 569/12 Lạc Long Quân",
    "price": "5tr3",
    "price1": "5.300.000",
    "price2": "5.300.000",
    "type": null
  },
  {
    "id": "1773513332773",
    "address": "số 16, ngõ 603, ngách 569/12 Lạc Long Quân",
    "price": "5tr3",
    "price1": "5.300.000",
    "price2": "5.300.000",
    "type": null
  },
  {
    "id": "1773513513514",
    "address": "số 16, ngõ 603, ngách 569/12 Lạc Long Quân",
    "price": "4tr7",
    "price1": "4.700.000",
    "price2": "4.700.000",
    "type": null
  },
  {
    "id": "1773515686027",
    "address": "460 Thuỵ Khuê - Tây Hồ",
    "price": "7tr5",
    "price1": "7.500.000",
    "price2": "7.500.000",
    "type": null
  },
  {
    "id": "1773538535019",
    "address": "số 2 ngõ 236/7 Âu Cơ, Hồng Hà, Hà Nội",
    "price": "7tr5",
    "price1": "7.500.000",
    "price2": "7.500.000",
    "type": "1n1k"
  },
  {
    "id": "1773538629620",
    "address": "số 2 ngõ 236/7 Âu Cơ, Hồng Hà, Hà Nội",
    "price": "9 triệu",
    "price1": "9.000.000",
    "price2": "9.000.000",
    "type": "1n1k"
  },
  {
    "id": "1773538691664",
    "address": "số 2 ngõ 236/7 Âu Cơ, Hồng Hà, Hà Nội",
    "price": "7tr5",
    "price1": "7.500.000",
    "price2": "7.500.000",
    "type": "1n1k"
  },
  {
    "id": "1773538791494",
    "address": "34 âu cơ, Tây Hồ",
    "price": "6 triệu",
    "price1": "6.000.000",
    "price2": "6.000.000",
    "type": "studio"
  },
  {
    "id": "1773539030559",
    "address": "34 âu cơ, Tây Hồ",
    "price": "4tr8",
    "price1": "4.800.000",
    "price2": "4.800.000",
    "type": "studio"
  },
  {
    "id": "1773540383704",
    "address": "số 2 ngõ 236/7 Âu Cơ, Hồng Hà, Hà Nội",
    "price": "7tr5-9tr",
    "price1": "7.500.000",
    "price2": "9.000.000",
    "type": "1n1k"
  },
  {
    "id": "1773540712797",
    "address": "Số 2B, ngách 46, Ngõ 445 Lạc Long Quân, Phường Xuân La, Q. Tây Hồ, Tp. Hà Nội",
    "price": "6tr2",
    "price1": "6.200.000",
    "price2": "6.800.000",
    "type": "studio"
  },
  {
    "id": "1773540795057",
    "address": "Số 48 ngõ 445 Lạc Long Quân, Tây Hồ, Hà Nội",
    "price": "8tr5",
    "price1": "8.500.000",
    "price2": "8.500.000",
    "type": "2N1K"
  },
  {
    "id": "1773543454412",
    "address": "số 32 ngõ 167 Thuỵ Khuê, Tây hồ",
    "price": "6tr5",
    "price1": "6.500.000",
    "price2": "6.500.000",
    "type": "studio"
  },
  {
    "id": "1773544567661",
    "address": "ngõ 167 Thuỵ Khuê, tây hồ",
    "price": "6tr5/tháng",
    "price1": "6.500.000",
    "price2": "6.500.000",
    "type": "studio"
  },
  {
    "id": "1773546462526",
    "address": "561A Lạc Long Quân- Quận: Tây Hồ",
    "price": "5tr",
    "price1": "5.000.000",
    "price2": "5.000.000",
    "type": "studio"
  },
  {
    "id": "1773548909702",
    "address": "442 Âu Cơ, TÂY HỒ",
    "price": "4tr8",
    "price1": "4.800.000",
    "price2": "4.800.000",
    "type": null
  },
  {
    "id": "1773548918870",
    "address": "15/351 Âu Cơ, Nhật Tân, Tây Hồ",
    "price": "4tr9",
    "price1": "4.900.000",
    "price2": "4.900.000",
    "type": null
  },
  {
    "id": "1773554716686",
    "address": "Trịnh Công Sơn ,Tây Hồ ,Hà Nội",
    "price": "11tr",
    "price1": "11.000.000",
    "price2": "11.000.000",
    "type": "1k1n"
  },
  {
    "id": "1773555028818",
    "address": "Nhà A1 – Số 32 ngõ 61 Lạc Long Quân - Tây hồ",
    "price": "5tr8",
    "price1": "5.800.000",
    "price2": "5.800.000",
    "type": "studio"
  },
  {
    "id": "1773555994974",
    "address": "số 2 ngõ 236/7 Âu Cơ, Hồng Hà, Hà Nội",
    "price": "7tr5 - 9tr",
    "price1": "7.500.000",
    "price2": "9.000.000",
    "type": "1n1k, studio"
  },
  {
    "id": "1773556088708",
    "address": "442/3/6B Âu Cơ - Tây Hồ",
    "price": "4tr5,4tr8",
    "price1": "4.500.000",
    "price2": "4.800.000",
    "type": "studio"
  },
  {
    "id": "1773559276165",
    "address": "Số 21 ngõ 445 Lạc Long Quân - Tây Hồ",
    "price": "6tr1,6tr5",
    "price1": "6.100.000",
    "price2": "6.500.000",
    "type": "1n1k"
  },
  {
    "id": "1773562834432",
    "address": "442/3/6B Âu Cơ - Tây Hồ",
    "price": "4tr5 - 4tr8",
    "price1": "4.500.000",
    "price2": "4.800.000",
    "type": "studio"
  },
  {
    "id": "1773564325771",
    "address": "Ngõ 89 Tứ Liên - Tây Hồ",
    "price": "10tr",
    "price1": "10.000.000",
    "price2": "10.000.000",
    "type": "2N1K"
  },
  {
    "id": "1773566212005",
    "address": "số 03 Nguyễn Hoàng Tôn, Xuân La, Tây Hồ",
    "price": "8tr",
    "price1": "8.000.000",
    "price2": "8.000.000",
    "type": "2n1k2wc"
  },
  {
    "id": "1773568537165",
    "address": "số 46 Lạc Long Quân, Tây Hồ",
    "price": "7tr5",
    "price1": "7.500.000",
    "price2": "7.500.000",
    "type": "1n1k"
  },
  {
    "id": "1773568542082",
    "address": "565 Lạc Long Quân - Tây Hồ",
    "price": "3tr9",
    "price1": "3.900.000",
    "price2": "3.900.000",
    "type": "studio"
  },
  {
    "id": "1773568575350",
    "address": "565 Lạc Long Quân - Tây Hồ",
    "price": "4tr5",
    "price1": "4.500.000",
    "price2": "4.500.000",
    "type": "1n1k"
  },
  {
    "id": "1773569211897",
    "address": "Ngõ 218 Lạc Long Quân, Tây Hồ",
    "price": "9tr2",
    "price1": "9.200.000",
    "price2": "9.200.000",
    "type": "1n1k"
  },
  {
    "id": "1773572808894",
    "address": "376/43 Thuỵ Khuê, Tây Hồ, Hà Nội",
    "price": "3tr6",
    "price1": "3.600.000",
    "price2": "3.600.000",
    "type": "studio"
  },
  {
    "id": "1773587645014",
    "address": "Ngõ 71 Trịnh Công Sơn- Quận: Tây Hồ",
    "price": "10tr",
    "price1": "10.000.000",
    "price2": "10.000.000",
    "type": "2n1k"
  },
  {
    "id": "1773587901065",
    "address": "2/4 An Dương Vương - Quận: Tây Hồ",
    "price": "3tr5-p401,404, 4tr-p403, 2tr7-p502, 2tr9-p205",
    "price1": "2.700.000",
    "price2": "4.000.000",
    "type": "đơn kk"
  },
  {
    "id": "1773587947438",
    "address": "2/4 An Dương Vương - Quận: Tây Hồ",
    "price": "5tr5-p503",
    "price1": "5.500.000",
    "price2": "5.500.000",
    "type": "2n1k"
  },
  {
    "id": "1773587973399",
    "address": "số 28 Từ Hoa - Tây Hồ",
    "price": "5tr-p6tr8",
    "price1": "5.000.000",
    "price2": "6.000.000",
    "type": "studio"
  },
  {
    "id": "1773588829202",
    "address": "Số 8B Ngõ 228 Âu cơ, Tây Hồ",
    "price": "7tr",
    "price1": "7.000.000",
    "price2": "7.000.000",
    "type": null
  },
  {
    "id": "1773588842524",
    "address": "225 Âu Cơ, Tây Hồ",
    "price": "8tr5",
    "price1": "8.500.000",
    "price2": "8.500.000",
    "type": null
  },
  {
    "id": "1773588848837",
    "address": "5 Ngõ 99 Âu cơ, P. Tây Hồ",
    "price": "7tr-p203",
    "price1": "7.000.000",
    "price2": "7.000.000",
    "type": "studio"
  },
  {
    "id": "1773588925797",
    "address": "5 Ngõ 99 Âu cơ, P. Tây Hồ",
    "price": "5tr5-p101tr3",
    "price1": "5.500.000",
    "price2": "5.500.000",
    "type": "studio"
  },
  {
    "id": "1773588930555",
    "address": "Số 58 ngõ 259 Trích Sài, Tây Hồ",
    "price": "3tr3",
    "price1": "3.300.000",
    "price2": "3.300.000",
    "type": null
  },
  {
    "id": "1773588959740",
    "address": "2D Ngõ 377 Âu cơ, Tây Hồ",
    "price": "5tr5-p501\n4tr2-p101",
    "price1": "4.200.000",
    "price2": "5.500.000",
    "type": "studio"
  },
  {
    "id": "1773589160489",
    "address": "Nhà 6B ngõ 690 Lạc Long Quân, Tây Hồ",
    "price": "6tr-p601",
    "price1": "6.000.000",
    "price2": "6.000.000",
    "type": null
  },
  {
    "id": "1773589374731",
    "address": "26 Ngõ 35A Tứ Liên, Tây Hồ",
    "price": "4tr-p101",
    "price1": "4.000.000",
    "price2": "4.000.000",
    "type": "studio"
  },
  {
    "id": "1773589383326",
    "address": "3B ngõ 32/18 Tô Ngọc Vân, Tây Hồ",
    "price": "8tr-p701\n7tr6-p602",
    "price1": "7.600.000",
    "price2": "8.000.000",
    "type": null
  },
  {
    "id": "1773589686152",
    "address": "Số 21 ngõ 445 Lạc Long Quân, Tây Hồ",
    "price": "6tr1 - 6tr5",
    "price1": "6.100.000",
    "price2": "6.500.000",
    "type": null
  },
  {
    "id": "1773589697692",
    "address": "21 ngõ 445 Lạc Long Quân, Tây Hồ",
    "price": "6tr1-p204\n6tr5-p305",
    "price1": "6.100.000",
    "price2": "6.500.000",
    "type": null
  },
  {
    "id": "1773589973135",
    "address": "Ngõ 218 Lạc Long Quân, Tây Hồ",
    "price": "8tr8",
    "price1": "8.800.000",
    "price2": "8.800.000",
    "type": null
  },
  {
    "id": "1773591007992",
    "address": "236 Âu Cơ, Tây Hồ",
    "price": "3tr7",
    "price1": "3.700.000",
    "price2": "3.700.000",
    "type": "studio"
  },
  {
    "id": "1773592769518",
    "address": "6/38/35 Ngõ 89 Lạc Long Quân, Tây Hồ",
    "price": "4tr1",
    "price1": "4.100.000",
    "price2": "4.100.000",
    "type": null
  },
  {
    "id": "1773593380494",
    "address": "Số 140 mặt đường Yên Phụ nhỏ, Tây Hồ",
    "price": "9tr5 - 11tr - 11tr5",
    "price1": "9.500.000",
    "price2": "11.500.000",
    "type": "2n1k"
  },
  {
    "id": "1773595967126",
    "address": "28 Tứ Liên, Tây Hồ",
    "price": "7tr5 tầng 2",
    "price1": "7.500.000",
    "price2": "7.500.000",
    "type": null
  },
  {
    "id": "1773602399208",
    "address": "Ngõ 79 An Dương Vương, Tây Hồ",
    "price": "8tr - Tầng 5",
    "price1": "8.000.000",
    "price2": "8.000.000",
    "type": "2n1k"
  },
  {
    "id": "1773606205621",
    "address": "442/3/6B Âu Cơ, Tây Hồ",
    "price": "4tr8 ( Ban Công View)\n4tr5",
    "price1": "4.500.000",
    "price2": "4.800.000",
    "type": null
  },
  {
    "id": "1773618974658",
    "address": "77 Xuân La, Tây Hồ",
    "price": "5tr5",
    "price1": "5.500.000",
    "price2": "5.500.000",
    "type": null
  },
  {
    "id": "1773619010907",
    "address": "565 Lạc Long Quân, Tây Hồ",
    "price": "6tr",
    "price1": "6.000.000",
    "price2": "6.000.000",
    "type": null
  },
  {
    "id": "1773619028782",
    "address": "236 Âu Cơ, Tây Hồ",
    "price": "3tr7",
    "price1": "3.700.000",
    "price2": "3.700.000",
    "type": null
  },
  {
    "id": "1773624784249",
    "address": "Số 17 ngõ 105 Phú Xá, Tây Hồ",
    "price": "4tr5- P303",
    "price1": "4.500.000",
    "price2": "4.500.000",
    "type": "gác xép"
  },
  {
    "id": "1773624804996",
    "address": "Số 48 ngõ 445 Lạc Long Quân, Tây Hồ",
    "price": "8tr5",
    "price1": "8.500.000",
    "price2": "8.500.000",
    "type": "2n1k"
  },
  {
    "id": "1773624812044",
    "address": "Số 2B, ngách 46 ngõ 445 Lạc Long Quân, Tây Hồ",
    "price": "6tr8",
    "price1": "6.800.000",
    "price2": "6.800.000",
    "type": null
  },
  {
    "id": "1773624830666",
    "address": "Số 2B, ngách 46 ngõ 445 Lạc Long Quân, Tây Hồ",
    "price": "6tr2",
    "price1": "6.200.000",
    "price2": "6.200.000",
    "type": "studio"
  },
  {
    "id": "1773626748890",
    "address": "6/38/35 Ngõ 89 Lạc Long Quân, Tây Hồ",
    "price": "4tr1",
    "price1": "4.100.000",
    "price2": "4.100.000",
    "type": null
  },
  {
    "id": "1773629612396",
    "address": "ngõ 99 Xuân La (236 Võ Chí Công), Tây Hồ",
    "price": "10tr- 2n1k1nvs",
    "price1": "10.000.000",
    "price2": "10.000.000",
    "type": "2n1k"
  },
  {
    "id": "1773629875574",
    "address": "ngõ 99 Xuân La (236 Võ Chí Công), Tây Hồ",
    "price": "6tr",
    "price1": "6.000.000",
    "price2": "6.000.000",
    "type": null
  },
  {
    "id": "1773633990017",
    "address": "Số 25B ngõ 210A Võ Chí Công, Tây Hồ",
    "price": "5tr5\n6tr5",
    "price1": "5.500.000",
    "price2": "6.500.000",
    "type": "studio, gác xép"
  },
  {
    "id": "1773634952918",
    "address": "Ngõ 8 Võng Thị, Tây Hồ",
    "price": "7tr3",
    "price1": "7.300.000",
    "price2": "7.300.000",
    "type": null
  },
  {
    "id": "1773636067819",
    "address": "Ngõ 442/3 Âu Cơ, Tây Hồ",
    "price": "4tr5 - 4tr8",
    "price1": "4.500.000",
    "price2": "4.800.000",
    "type": null
  },
  {
    "id": "1773636223269",
    "address": "31/28 Tứ Liên, Tây Hồ",
    "price": "5tr5 - 6tr7",
    "price1": "5.500.000",
    "price2": "6.700.000",
    "type": null
  },
  {
    "id": "1773636297925",
    "address": "74/28 Tứ Liên, Tây Hồ",
    "price": "4tr5 - 7tr3",
    "price1": "4.500.000",
    "price2": "7.300.000",
    "type": null
  },
  {
    "id": "1773636569147",
    "address": "179 Phố Nguyễn Đình Thi, Tây Hồ",
    "price": "5tr",
    "price1": "5.000.000",
    "price2": "5.000.000",
    "type": "studio"
  },
  {
    "id": "1773637233989",
    "address": "Ngõ 236 Âu cơ, Tây hồ",
    "price": "3tr7",
    "price1": "3.700.000",
    "price2": "3.700.000",
    "type": null
  },
  {
    "id": "1773642262797",
    "address": "56 Vũ Miên, Tây Hồ",
    "price": "10tr",
    "price1": "10.000.000",
    "price2": "10.000.000",
    "type": "2n1k"
  },
  {
    "id": "1773642370566",
    "address": "Số 91C ngõ 91 Đồng Cổ, Thuỵ Khuê, Tây Hồ",
    "price": "6tr, 5tr5, 5tr",
    "price1": "5.000.000",
    "price2": "6.000.000",
    "type": "studio"
  },
  {
    "id": "1773642700075",
    "address": "Ngõ 29 Võng Thị, Tây Hồ",
    "price": "6tr5, 6tr5tr5",
    "price1": "6.500.000",
    "price2": "6.500.000",
    "type": "studio"
  },
  {
    "id": "1773646663135",
    "address": "Ngách 30/15 Ngõ 189 An Dương Vương (108 Nghi Tàm), Tây Hồ",
    "price": "8tr5",
    "price1": "8.500.000",
    "price2": "8.500.000",
    "type": "2n1k"
  },
  {
    "id": "1773647012486",
    "address": "Ngách 30/15 Ngõ 189 An Dương Vương (108 Nghi Tàm), Tây Hồ",
    "price": "8tr5",
    "price1": "8.500.000",
    "price2": "8.500.000",
    "type": "2n1k"
  },
  {
    "id": "1773647037845",
    "address": "Ngách 30/15 Ngõ 189 An Dương Vương (108 Nghi Tàm), Tây Hồ",
    "price": "8tr5",
    "price1": "8.500.000",
    "price2": "8.500.000",
    "type": "2n1k"
  },
  {
    "id": "1773647584169",
    "address": "Ngõ 603/2 Lạc Long Quân, Tây Hồ",
    "price": "5tr8, 6tr5",
    "price1": "5.800.000",
    "price2": "6.500.000",
    "type": "studio"
  },
  {
    "id": "1773647928939",
    "address": "Số 7 Ngõ 96 Võ Chí Công, Tây Hồ",
    "price": "7tr5, 6tr5",
    "price1": "6.500.000",
    "price2": "7.500.000",
    "type": null
  },
  {
    "id": "1773648175648",
    "address": "Số 210 Lạc Long Quân, Tây Hồ",
    "price": "3tr9",
    "price1": "3.900.000",
    "price2": "3.900.000",
    "type": "studio"
  },
  {
    "id": "1773648602376",
    "address": "Ngõ 79 An Dương Vương, Tây Hồ",
    "price": "8tr",
    "price1": "8.000.000",
    "price2": "8.000.000",
    "type": "2n1k"
  },
  {
    "id": "1773650717520",
    "address": "Ngõ 530 Thụy Khuê, Tây Hồ",
    "price": "7tr3",
    "price1": "7.300.000",
    "price2": "7.300.000",
    "type": null
  },
  {
    "id": "1773651899015",
    "address": "Ngõ 61 Lạc Long Quân, Tây Hồ",
    "price": "4tr9 - 5tr1 - 5tr3- 5tr7",
    "price1": "4.900.000",
    "price2": "5.700.000",
    "type": "studio"
  },
  {
    "id": "1773652702554",
    "address": "Ngách 30/15 Ngõ 189 An Dương Vương (108 Nghi Tàm), Tây Hồ",
    "price": "8tr5",
    "price1": "8.500.000",
    "price2": "8.500.000",
    "type": "2n1k"
  },
  {
    "id": "1773657094128",
    "address": "Số 201 Âu Cơ, Tây Hồ",
    "price": "3tr",
    "price1": "3.000.000",
    "price2": "3.000.000",
    "type": null
  },
  {
    "id": "1773661641096",
    "address": "37 Võng Thị, Tây Hồ",
    "price": "9tr",
    "price1": "9.000.000",
    "price2": "9.000.000",
    "type": null
  },
  {
    "id": "1773663849317",
    "address": "Số 6 ngõ 141 đường An Dương Vương, Tây Hồ",
    "price": "4tr2, 4tr, 4tr5",
    "price1": "4.000.000",
    "price2": "4.500.000",
    "type": "studio, gác xép"
  }
]